prcv/__init__.py
prcv/methods.py
prcv/misc.py
prcv/scale.py
prcv-1.2.1.dist-info/METADATA
prcv-1.2.1.dist-info/WHEEL
prcv-1.2.1.dist-info/licenses/LICENSE
prcv-1.2.1.dist-info/RECORD
