Metadata-Version: 2.4
Name: prcv
Version: 1.2.1
Summary: Implementation of Procrustes cross-validation in Python
Project-URL: Homepage, https://github.com/svkucheryavski/pcv
Project-URL: Bug Tracker, https://github.com/svkucheryavski/pcv/issues
Author-email: Sergey Kucheryavskiy <svkucheryavski@gmail.com>
License-File: LICENSE
Classifier: License :: OSI Approved :: MIT License
Classifier: Operating System :: OS Independent
Classifier: Programming Language :: Python :: 3
Requires-Python: >=3.7
